LICENSE
MANIFEST.in
README.rst
setup.cfg
setup.py
robob/__init__.py
robob/cli.py
robob/component.py
robob/context.py
robob/driver.py
robob/factories.py
robob/logger.py
robob/logpipe.py
robob/metrics.py
robob/reporter.py
robob/specs.py
robob/stream.py
robob/util.py
robob.egg-info/PKG-INFO
robob.egg-info/SOURCES.txt
robob.egg-info/dependency_links.txt
robob.egg-info/entry_points.txt
robob.egg-info/pbr.json
robob.egg-info/requires.txt
robob.egg-info/top_level.txt
robob/access/__init__.py
robob/access/local.py
robob/access/ssh.py
robob/aggregate/__init__.py
robob/aggregate/avg.py
robob/aggregate/bw.py
robob/aggregate/count.py
robob/aggregate/max.py
robob/aggregate/min.py
robob/aggregate/sum.py
robob/parser/__init__.py
robob/parser/mpstat.py
robob/parser/regex.py
robob/parser/split.py
robob/pipe/__init__.py
robob/pipe/app.py
robob/pipe/bashwrap.py
robob/pipe/filedel.py
robob/pipe/filegen.py
robob/pipe/script.py