Metadata-Version: 1.1
Name: robob
Version: 0.2.1
Summary: A python tool for simplifying collection of measurements over repetitive tasks
Home-page: https://github.com/wavesoft/robob
Author: Ioannis Charalampidis
Author-email: johnys2@gmail.com
License: Apache-2.0
Keywords: automation benchmark scripting test
Platform: UNKNOWN
Classifier: Development Status :: 4 - Beta
Classifier: Intended Audience :: Science/Research
Classifier: Intended Audience :: System Administrators
Classifier: Topic :: Software Development :: Quality Assurance
Classifier: Topic :: Software Development :: Testing
Classifier: Topic :: Utilities
Classifier: License :: OSI Approved :: Apache Software License
Classifier: Programming Language :: Python :: 2
Classifier: Programming Language :: Python :: 2.6
Classifier: Programming Language :: Python :: 2.7
Classifier: Programming Language :: Python :: 3
Classifier: Programming Language :: Python :: 3.3
Classifier: Programming Language :: Python :: 3.4
Classifier: Programming Language :: Python :: 3.5
